{
	"cohorts": {
		"2023": [
			{ "month": 0, "ltv": 250 },
			{ "month": 1, "ltv": 265 },
			{ "month": 2, "ltv": 278 },
			{ "month": 3, "ltv": 290 },
			{ "month": 4, "ltv": 302 },
			{ "month": 5, "ltv": 315 },
			{ "month": 6, "ltv": 328 },
			{ "month": 7, "ltv": 340 },
			{ "month": 8, "ltv": 352 },
			{ "month": 9, "ltv": 363 },
			{ "month": 10, "ltv": 374 },
			{ "month": 11, "ltv": 385 },
			{ "month": 12, "ltv": 395 },
			{ "month": 13, "ltv": 402 },
			{ "month": 14, "ltv": 408 },
			{ "month": 15, "ltv": 412 },
			{ "month": 16, "ltv": 414 },
			{ "month": 17, "ltv": 415.5 },
			{ "month": 18, "ltv": 416.2 },
			{ "month": 19, "ltv": 416.8 }
		],
		"2024": [
			{ "month": 0, "ltv": 180 },
			{ "month": 1, "ltv": 190 },
			{ "month": 2, "ltv": 198 },
			{ "month": 3, "ltv": 205 },
			{ "month": 4, "ltv": 212 },
			{ "month": 5, "ltv": 218 },
			{ "month": 6, "ltv": 224 },
			{ "month": 7, "ltv": 229 },
			{ "month": 8, "ltv": 233 },
			{ "month": 9, "ltv": 236 },
			{ "month": 10, "ltv": 238.5 },
			{ "month": 11, "ltv": 240 },
			{ "month": 12, "ltv": 240.8 },
			{ "month": 13, "ltv": 241.2 },
			{ "month": 14, "ltv": 241.5 },
			{ "month": 15, "ltv": 241.6 },
			{ "month": 16, "ltv": 241.7 },
			{ "month": 17, "ltv": 241.75 },
			{ "month": 18, "ltv": 241.78 },
			{ "month": 19, "ltv": 241.8 }
		],
		"2025": [
			{ "month": 0, "ltv": 150 },
			{ "month": 1, "ltv": 158 },
			{ "month": 2, "ltv": 165 },
			{ "month": 3, "ltv": 171 },
			{ "month": 4, "ltv": 176 },
			{ "month": 5, "ltv": 180 },
			{ "month": 6, "ltv": 183 },
			{ "month": 7, "ltv": 185 },
			{ "month": 8, "ltv": 186.5 },
			{ "month": 9, "ltv": 187.5 },
			{ "month": 10, "ltv": 188 },
			{ "month": 11, "ltv": 188.3 },
			{ "month": 12, "ltv": 188.5 },
			{ "month": 13, "ltv": 188.6 },
			{ "month": 14, "ltv": 188.7 },
			{ "month": 15, "ltv": 188.75 },
			{ "month": 16, "ltv": 188.78 },
			{ "month": 17, "ltv": 188.8 },
			{ "month": 18, "ltv": 188.82 },
			{ "month": 19, "ltv": 188.85 }
		]
	}
}

